PrivateCode/__init__.py
PrivateCode/privatecode.py
PrivateCode-1.0.0.dist-info/LICENSE
PrivateCode-1.0.0.dist-info/METADATA
PrivateCode-1.0.0.dist-info/WHEEL
PrivateCode-1.0.0.dist-info/top_level.txt
PrivateCode-1.0.0.dist-info/RECORD
