Metadata-Version: 2.1
Name: PrivateCode
Version: 1.0.0
Summary: PrivateCode is a Python library that provides a decorator to make a function, method, or class private.
Home-page: https://github.com/LixNew2/PrivateCode
Author: LixNew
Author-email: lixnew2@gmail.com
Classifier: Programming Language :: Python :: 3
Classifier: License :: OSI Approved :: MIT License
Classifier: Operating System :: OS Independent
Requires-Python: >=3.6
License-File: LICENSE
